{
  "game_id": 15908510,
  "date": "2025-02-12",
  "home_team": {
    "name": "Houston Rockets",
    "abbreviation": "HOU",
    "score": 119,
    "players": [
      {
        "player_id": 56677825,
        "player_name": "Amen Thompson",
        "position": "G-F",
        "MINUTES": 42.0,
        "FGM": 7.0,
        "FGA": 13.0,
        "FG3M": 0.0,
        "FG3A": 1.0,
        "FTM": 4.0,
        "FTA": 7.0,
        "OREB": 2.0,
        "DREB": 8.0,
        "REB": 10.0,
        "AST": 11.0,
        "STL": 2.0,
        "BLK": 2.0,
        "TOV": 3.0,
        "PF": 0.0,
        "PTS": 18.0,
        "PLUS_MINUS": 0.0
      },
      {
        "player_id": 17896062,
        "player_name": "Alperen Sengun",
        "position": "F-C",
        "MINUTES": 38.0,
        "FGM": 7.0,
        "FGA": 12.0,
        "FG3M": 0.0,
        "FG3A": 2.0,
        "FTM": 3.0,
        "FTA": 6.0,
        "OREB": 2.0,
        "DREB": 11.0,
        "REB": 13.0,
        "AST": 5.0,
        "STL": 2.0,
        "BLK": 1.0,
        "TOV": 2.0,
        "PF": 3.0,
        "PTS": 17.0,
        "PLUS_MINUS": 0.0
      },
      {
        "player_id": 17895966,
        "player_name": "Jalen Green",
        "position": "G",
        "MINUTES": 37.0,
        "FGM": 8.0,
        "FGA": 21.0,
        "FG3M": 4.0,
        "FG3A": 15.0,
        "FTM": 2.0,
        "FTA": 3.0,
        "OREB": 2.0,
        "DREB": 1.0,
        "REB": 3.0,
        "AST": 5.0,
        "STL": 0.0,
        "BLK": 1.0,
        "TOV": 2.0,
        "PF": 1.0,
        "PTS": 22.0,
        "PLUS_MINUS": 0.0
      },
      {
        "player_id": 38017695,
        "player_name": "Tari Eason",
        "position": "F",
        "MINUTES": 34.0,
        "FGM": 11.0,
        "FGA": 16.0,
        "FG3M": 3.0,
        "FG3A": 5.0,
        "FTM": 0.0,
        "FTA": 1.0,
        "OREB": 4.0,
        "DREB": 5.0,
        "REB": 9.0,
        "AST": 4.0,
        "STL": 3.0,
        "BLK": 0.0,
        "TOV": 1.0,
        "PF": 2.0,
        "PTS": 25.0,
        "PLUS_MINUS": 0.0
      },
      {
        "player_id": 66,
        "player_name": "Dillon Brooks",
        "position": "G-F",
        "MINUTES": 31.0,
        "FGM": 5.0,
        "FGA": 13.0,
        "FG3M": 4.0,
        "FG3A": 9.0,
        "FTM": 4.0,
        "FTA": 4.0,
        "OREB": 1.0,
        "DREB": 1.0,
        "REB": 2.0,
        "AST": 3.0,
        "STL": 2.0,
        "BLK": 0.0,
        "TOV": 1.0,
        "PF": 4.0,
        "PTS": 18.0,
        "PLUS_MINUS": 0.0
      },
      {
        "player_id": 56677831,
        "player_name": "Cam Whitmore",
        "position": "F",
        "MINUTES": 22.0,
        "FGM": 2.0,
        "FGA": 10.0,
        "FG3M": 0.0,
        "FG3A": 5.0,
        "FTM": 0.0,
        "FTA": 0.0,
        "OREB": 0.0,
        "DREB": 2.0,
        "REB": 2.0,
        "AST": 3.0,
        "STL": 0.0,
        "BLK": 0.0,
        "TOV": 0.0,
        "PF": 2.0,
        "PTS": 4.0,
        "PLUS_MINUS": 0.0
      },
      {
        "player_id": 3547301,
        "player_name": "Jae'Sean Tate",
        "position": "F",
        "MINUTES": 15.0,
        "FGM": 2.0,
        "FGA": 5.0,
        "FG3M": 1.0,
        "FG3A": 4.0,
        "FTM": 0.0,
        "FTA": 0.0,
        "OREB": 1.0,
        "DREB": 0.0,
        "REB": 1.0,
        "AST": 0.0,
        "STL": 0.0,
        "BLK": 0.0,
        "TOV": 1.0,
        "PF": 1.0,
        "PTS": 5.0,
        "PLUS_MINUS": 0.0
      },
      {
        "player_id": 1028028519,
        "player_name": "Reed Sheppard",
        "position": "G",
        "MINUTES": 11.0,
        "FGM": 2.0,
        "FGA": 2.0,
        "FG3M": 1.0,
        "FG3A": 1.0,
        "FTM": 0.0,
        "FTA": 0.0,
        "OREB": 0.0,
        "DREB": 1.0,
        "REB": 1.0,
        "AST": 1.0,
        "STL": 1.0,
        "BLK": 0.0,
        "TOV": 0.0,
        "PF": 2.0,
        "PTS": 5.0,
        "PLUS_MINUS": 0.0
      },
      {
        "player_id": 3,
        "player_name": "Steven Adams",
        "position": "C",
        "MINUTES": 10.0,
        "FGM": 2.0,
        "FGA": 5.0,
        "FG3M": 0.0,
        "FG3A": 0.0,
        "FTM": 1.0,
        "FTA": 3.0,
        "OREB": 5.0,
        "DREB": 1.0,
        "REB": 6.0,
        "AST": 0.0,
        "STL": 0.0,
        "BLK": 0.0,
        "TOV": 1.0,
        "PF": 0.0,
        "PTS": 5.0,
        "PLUS_MINUS": 0.0
      },
      {
        "player_id": 1028243921,
        "player_name": "N'Faly Dante",
        "position": "C",
        "MINUTES": 0.0,
        "FGM": 0.0,
        "FGA": 0.0,
        "FG3M": 0.0,
        "FG3A": 0.0,
        "FTM": 0.0,
        "FTA": 0.0,
        "OREB": 0.0,
        "DREB": 0.0,
        "REB": 0.0,
        "AST": 0.0,
        "STL": 0.0,
        "BLK": 0.0,
        "TOV": 0.0,
        "PF": 0.0,
        "PTS": 0.0,
        "PLUS_MINUS": 0.0
      },
      {
        "player_id": 188,
        "player_name": "Jeff Green",
        "position": "F",
        "MINUTES": 0.0,
        "FGM": 0.0,
        "FGA": 0.0,
        "FG3M": 0.0,
        "FG3A": 0.0,
        "FTM": 0.0,
        "FTA": 0.0,
        "OREB": 0.0,
        "DREB": 0.0,
        "REB": 0.0,
        "AST": 0.0,
        "STL": 0.0,
        "BLK": 0.0,
        "TOV": 0.0,
        "PF": 0.0,
        "PTS": 0.0,
        "PLUS_MINUS": 0.0
      },
      {
        "player_id": 213,
        "player_name": "Aaron Holiday",
        "position": "G",
        "MINUTES": 0.0,
        "FGM": 0.0,
        "FGA": 0.0,
        "FG3M": 0.0,
        "FG3A": 0.0,
        "FTM": 0.0,
        "FTA": 0.0,
        "OREB": 0.0,
        "DREB": 0.0,
        "REB": 0.0,
        "AST": 0.0,
        "STL": 0.0,
        "BLK": 0.0,
        "TOV": 0.0,
        "PF": 0.0,
        "PTS": 0.0,
        "PLUS_MINUS": 0.0
      },
      {
        "player_id": 19465326,
        "player_name": "Jock Landale",
        "position": "C",
        "MINUTES": 0.0,
        "FGM": 0.0,
        "FGA": 0.0,
        "FG3M": 0.0,
        "FG3A": 0.0,
        "FTM": 0.0,
        "FTA": 0.0,
        "OREB": 0.0,
        "DREB": 0.0,
        "REB": 0.0,
        "AST": 0.0,
        "STL": 0.0,
        "BLK": 0.0,
        "TOV": 0.0,
        "PF": 0.0,
        "PTS": 0.0,
        "PLUS_MINUS": 0.0
      },
      {
        "player_id": 458,
        "player_name": "Fred VanVleet",
        "position": "G",
        "MINUTES": 0.0,
        "FGM": 0.0,
        "FGA": 0.0,
        "FG3M": 0.0,
        "FG3A": 0.0,
        "FTM": 0.0,
        "FTA": 0.0,
        "OREB": 0.0,
        "DREB": 0.0,
        "REB": 0.0,
        "AST": 0.0,
        "STL": 0.0,
        "BLK": 0.0,
        "TOV": 0.0,
        "PF": 0.0,
        "PTS": 0.0,
        "PLUS_MINUS": 0.0
      },
      {
        "player_id": 47738533,
        "player_name": "Jeenathan Williams",
        "position": "G",
        "MINUTES": 0.0,
        "FGM": 0.0,
        "FGA": 0.0,
        "FG3M": 0.0,
        "FG3A": 0.0,
        "FTM": 0.0,
        "FTA": 0.0,
        "OREB": 0.0,
        "DREB": 0.0,
        "REB": 0.0,
        "AST": 0.0,
        "STL": 0.0,
        "BLK": 0.0,
        "TOV": 0.0,
        "PF": 0.0,
        "PTS": 0.0,
        "PLUS_MINUS": 0.0
      },
      {
        "player_id": 1028255931,
        "player_name": "Jack McVeigh",
        "position": "G-F",
        "MINUTES": 0.0,
        "FGM": 0.0,
        "FGA": 0.0,
        "FG3M": 0.0,
        "FG3A": 0.0,
        "FTM": 0.0,
        "FTA": 0.0,
        "OREB": 0.0,
        "DREB": 0.0,
        "REB": 0.0,
        "AST": 0.0,
        "STL": 0.0,
        "BLK": 0.0,
        "TOV": 0.0,
        "PF": 0.0,
        "PTS": 0.0,
        "PLUS_MINUS": 0.0
      },
      {
        "player_id": 38017684,
        "player_name": "Jabari Smith Jr.",
        "position": "F",
        "MINUTES": 0.0,
        "FGM": 0.0,
        "FGA": 0.0,
        "FG3M": 0.0,
        "FG3A": 0.0,
        "FTM": 0.0,
        "FTA": 0.0,
        "OREB": 0.0,
        "DREB": 0.0,
        "REB": 0.0,
        "AST": 0.0,
        "STL": 0.0,
        "BLK": 0.0,
        "TOV": 0.0,
        "PF": 0.0,
        "PTS": 0.0,
        "PLUS_MINUS": 0.0
      },
      {
        "player_id": 491,
        "player_name": "Cody Zeller",
        "position": "C",
        "MINUTES": 0.0,
        "FGM": 0.0,
        "FGA": 0.0,
        "FG3M": 0.0,
        "FG3A": 0.0,
        "FTM": 0.0,
        "FTA": 0.0,
        "OREB": 0.0,
        "DREB": 0.0,
        "REB": 0.0,
        "AST": 0.0,
        "STL": 0.0,
        "BLK": 0.0,
        "TOV": 0.0,
        "PF": 0.0,
        "PTS": 0.0,
        "PLUS_MINUS": 0.0
      }
    ]
  },
  "away_team": {
    "name": "Phoenix Suns",
    "abbreviation": "PHX",
    "score": 111,
    "players": [
      {
        "player_id": 140,
        "player_name": "Kevin Durant",
        "position": "F",
        "MINUTES": 42.0,
        "FGM": 15.0,
        "FGA": 22.0,
        "FG3M": 2.0,
        "FG3A": 5.0,
        "FTM": 5.0,
        "FTA": 5.0,
        "OREB": 0.0,
        "DREB": 5.0,
        "REB": 5.0,
        "AST": 9.0,
        "STL": 2.0,
        "BLK": 0.0,
        "TOV": 7.0,
        "PF": 5.0,
        "PTS": 37.0,
        "PLUS_MINUS": 0.0
      },
      {
        "player_id": 351,
        "player_name": "Royce O'Neale",
        "position": "F",
        "MINUTES": 35.0,
        "FGM": 5.0,
        "FGA": 9.0,
        "FG3M": 4.0,
        "FG3A": 5.0,
        "FTM": 0.0,
        "FTA": 0.0,
        "OREB": 0.0,
        "DREB": 4.0,
        "REB": 4.0,
        "AST": 0.0,
        "STL": 2.0,
        "BLK": 0.0,
        "TOV": 0.0,
        "PF": 2.0,
        "PTS": 14.0,
        "PLUS_MINUS": 0.0
      },
      {
        "player_id": 666451,
        "player_name": "Bol Bol",
        "position": "C",
        "MINUTES": 34.0,
        "FGM": 7.0,
        "FGA": 18.0,
        "FG3M": 1.0,
        "FG3A": 6.0,
        "FTM": 0.0,
        "FTA": 0.0,
        "OREB": 2.0,
        "DREB": 2.0,
        "REB": 4.0,
        "AST": 0.0,
        "STL": 1.0,
        "BLK": 2.0,
        "TOV": 1.0,
        "PF": 2.0,
        "PTS": 15.0,
        "PLUS_MINUS": 0.0
      },
      {
        "player_id": 249,
        "player_name": "Tyus Jones",
        "position": "G",
        "MINUTES": 33.0,
        "FGM": 4.0,
        "FGA": 11.0,
        "FG3M": 1.0,
        "FG3A": 3.0,
        "FTM": 1.0,
        "FTA": 2.0,
        "OREB": 2.0,
        "DREB": 3.0,
        "REB": 5.0,
        "AST": 6.0,
        "STL": 1.0,
        "BLK": 0.0,
        "TOV": 6.0,
        "PF": 2.0,
        "PTS": 10.0,
        "PLUS_MINUS": 0.0
      },
      {
        "player_id": 3547282,
        "player_name": "Nick Richards",
        "position": "C",
        "MINUTES": 28.0,
        "FGM": 5.0,
        "FGA": 6.0,
        "FG3M": 0.0,
        "FG3A": 0.0,
        "FTM": 1.0,
        "FTA": 2.0,
        "OREB": 4.0,
        "DREB": 9.0,
        "REB": 13.0,
        "AST": 0.0,
        "STL": 0.0,
        "BLK": 2.0,
        "TOV": 1.0,
        "PF": 3.0,
        "PTS": 11.0,
        "PLUS_MINUS": 0.0
      },
      {
        "player_id": 38017691,
        "player_name": "TyTy Washington Jr.",
        "position": "G",
        "MINUTES": 26.0,
        "FGM": 4.0,
        "FGA": 10.0,
        "FG3M": 1.0,
        "FG3A": 3.0,
        "FTM": 2.0,
        "FTA": 2.0,
        "OREB": 1.0,
        "DREB": 3.0,
        "REB": 4.0,
        "AST": 3.0,
        "STL": 1.0,
        "BLK": 0.0,
        "TOV": 1.0,
        "PF": 0.0,
        "PTS": 11.0,
        "PLUS_MINUS": 0.0
      },
      {
        "player_id": 371,
        "player_name": "Mason Plumlee",
        "position": "F-C",
        "MINUTES": 17.0,
        "FGM": 2.0,
        "FGA": 3.0,
        "FG3M": 0.0,
        "FG3A": 0.0,
        "FTM": 0.0,
        "FTA": 0.0,
        "OREB": 1.0,
        "DREB": 4.0,
        "REB": 5.0,
        "AST": 4.0,
        "STL": 0.0,
        "BLK": 0.0,
        "TOV": 0.0,
        "PF": 4.0,
        "PTS": 4.0,
        "PLUS_MINUS": 0.0
      },
      {
        "player_id": 38017727,
        "player_name": "Collin Gillespie",
        "position": "G",
        "MINUTES": 15.0,
        "FGM": 4.0,
        "FGA": 8.0,
        "FG3M": 1.0,
        "FG3A": 2.0,
        "FTM": 0.0,
        "FTA": 0.0,
        "OREB": 1.0,
        "DREB": 0.0,
        "REB": 1.0,
        "AST": 3.0,
        "STL": 0.0,
        "BLK": 1.0,
        "TOV": 0.0,
        "PF": 1.0,
        "PTS": 9.0,
        "PLUS_MINUS": 0.0
      },
      {
        "player_id": 1028025723,
        "player_name": "Ryan Dunn",
        "position": "F",
        "MINUTES": 10.0,
        "FGM": 0.0,
        "FGA": 2.0,
        "FG3M": 0.0,
        "FG3A": 2.0,
        "FTM": 0.0,
        "FTA": 0.0,
        "OREB": 0.0,
        "DREB": 2.0,
        "REB": 2.0,
        "AST": 0.0,
        "STL": 0.0,
        "BLK": 0.0,
        "TOV": 1.0,
        "PF": 0.0,
        "PTS": 0.0,
        "PLUS_MINUS": 0.0
      },
      {
        "player_id": 272,
        "player_name": "Damion Lee",
        "position": "G",
        "MINUTES": 0.0,
        "FGM": 0.0,
        "FGA": 0.0,
        "FG3M": 0.0,
        "FG3A": 0.0,
        "FTM": 0.0,
        "FTA": 0.0,
        "OREB": 0.0,
        "DREB": 0.0,
        "REB": 0.0,
        "AST": 0.0,
        "STL": 0.0,
        "BLK": 0.0,
        "TOV": 0.0,
        "PF": 0.0,
        "PTS": 0.0,
        "PLUS_MINUS": 0.0
      },
      {
        "player_id": 4197029,
        "player_name": "Vasilije Micic",
        "position": "G",
        "MINUTES": 0.0,
        "FGM": 0.0,
        "FGA": 0.0,
        "FG3M": 0.0,
        "FG3A": 0.0,
        "FTM": 0.0,
        "FTA": 0.0,
        "OREB": 0.0,
        "DREB": 0.0,
        "REB": 0.0,
        "AST": 0.0,
        "STL": 0.0,
        "BLK": 0.0,
        "TOV": 0.0,
        "PF": 0.0,
        "PTS": 0.0,
        "PLUS_MINUS": 0.0
      },
      {
        "player_id": 330,
        "player_name": "Monte Morris",
        "position": "G",
        "MINUTES": 0.0,
        "FGM": 0.0,
        "FGA": 0.0,
        "FG3M": 0.0,
        "FG3A": 0.0,
        "FTM": 0.0,
        "FTA": 0.0,
        "OREB": 0.0,
        "DREB": 0.0,
        "REB": 0.0,
        "AST": 0.0,
        "STL": 0.0,
        "BLK": 0.0,
        "TOV": 0.0,
        "PF": 0.0,
        "PTS": 0.0,
        "PLUS_MINUS": 0.0
      },
      {
        "player_id": 1028036515,
        "player_name": "Oso Ighodaro",
        "position": "F",
        "MINUTES": 0.0,
        "FGM": 0.0,
        "FGA": 0.0,
        "FG3M": 0.0,
        "FG3A": 0.0,
        "FTM": 0.0,
        "FTA": 0.0,
        "OREB": 0.0,
        "DREB": 0.0,
        "REB": 0.0,
        "AST": 0.0,
        "STL": 0.0,
        "BLK": 0.0,
        "TOV": 0.0,
        "PF": 0.0,
        "PTS": 0.0,
        "PLUS_MINUS": 0.0
      },
      {
        "player_id": 37,
        "player_name": "Bradley Beal",
        "position": "G",
        "MINUTES": 0.0,
        "FGM": 0.0,
        "FGA": 0.0,
        "FG3M": 0.0,
        "FG3A": 0.0,
        "FTM": 0.0,
        "FTA": 0.0,
        "OREB": 0.0,
        "DREB": 0.0,
        "REB": 0.0,
        "AST": 0.0,
        "STL": 0.0,
        "BLK": 0.0,
        "TOV": 0.0,
        "PF": 0.0,
        "PTS": 0.0,
        "PLUS_MINUS": 0.0
      },
      {
        "player_id": 57,
        "player_name": "Devin Booker",
        "position": "G",
        "MINUTES": 0.0,
        "FGM": 0.0,
        "FGA": 0.0,
        "FG3M": 0.0,
        "FG3A": 0.0,
        "FTM": 0.0,
        "FTA": 0.0,
        "OREB": 0.0,
        "DREB": 0.0,
        "REB": 0.0,
        "AST": 0.0,
        "STL": 0.0,
        "BLK": 0.0,
        "TOV": 0.0,
        "PF": 0.0,
        "PTS": 0.0,
        "PLUS_MINUS": 0.0
      },
      {
        "player_id": 1028178629,
        "player_name": "Jalen Bridges",
        "position": "F",
        "MINUTES": 0.0,
        "FGM": 0.0,
        "FGA": 0.0,
        "FG3M": 0.0,
        "FG3A": 0.0,
        "FTM": 0.0,
        "FTA": 0.0,
        "OREB": 0.0,
        "DREB": 0.0,
        "REB": 0.0,
        "AST": 0.0,
        "STL": 0.0,
        "BLK": 0.0,
        "TOV": 0.0,
        "PF": 0.0,
        "PTS": 0.0,
        "PLUS_MINUS": 0.0
      },
      {
        "player_id": 666748,
        "player_name": "Cody Martin",
        "position": "F",
        "MINUTES": 0.0,
        "FGM": 0.0,
        "FGA": 0.0,
        "FG3M": 0.0,
        "FG3A": 0.0,
        "FTM": 0.0,
        "FTA": 0.0,
        "OREB": 0.0,
        "DREB": 0.0,
        "REB": 0.0,
        "AST": 0.0,
        "STL": 0.0,
        "BLK": 0.0,
        "TOV": 0.0,
        "PF": 0.0,
        "PTS": 0.0,
        "PLUS_MINUS": 0.0
      },
      {
        "player_id": 8,
        "player_name": "Grayson Allen",
        "position": "G",
        "MINUTES": 0.0,
        "FGM": 0.0,
        "FGA": 0.0,
        "FG3M": 0.0,
        "FG3A": 0.0,
        "FTM": 0.0,
        "FTA": 0.0,
        "OREB": 0.0,
        "DREB": 0.0,
        "REB": 0.0,
        "AST": 0.0,
        "STL": 0.0,
        "BLK": 0.0,
        "TOV": 0.0,
        "PF": 0.0,
        "PTS": 0.0,
        "PLUS_MINUS": 0.0
      }
    ]
  }
}